{
  "animepahe": {
    "status": "online",
    "message": "Service is operational but slower than other sources.",
    "lastChecked": "2025-03-28T23:02:52.647337Z"
  },
  "animefox": {
    "status": "offline",
    "message": "Currently unavailable. Please check back later.",
    "lastChecked": "2025-03-28T23:02:52.647337Z"
  },
  "kaido": {
    "status": "online",
    "message": "Fully operational, including in India.",
    "lastChecked": "2025-03-28T23:02:52.647337Z"
  },
  "animekai": {
    "status": "online",
    "message": "Service is functional, but some anime may have issues.",
    "lastChecked": "2025-03-28T23:02:52.647337Z"
  },
  "hianime": {
    "status": "issues",
    "message": "Accessible but facing issues in India, possibly due to regional restrictions.",
    "lastChecked": "2025-03-28T23:02:52.647337Z"
  },
  "anify": {
    "status": "offline",
    "message": "Server is down. No ETA for recovery.",
    "lastChecked": "2025-03-28T23:02:52.647337Z"
  },
  "aniwatch": {
    "status": "issues",
    "message": "Service is working but facing accessibility issues in India, likely due to regional blocks.",
    "lastChecked": "2025-03-28T23:02:52.647337Z"
  }
}
